restclasses/__init__.py
restclasses-1.0.0.dist-info/LICENSE
restclasses-1.0.0.dist-info/METADATA
restclasses-1.0.0.dist-info/WHEEL
restclasses-1.0.0.dist-info/top_level.txt
restclasses-1.0.0.dist-info/zip-safe
restclasses-1.0.0.dist-info/RECORD
