Metadata-Version: 2.1
Name: restclasses
Version: 1.0.0
Summary: library for binding classes to HTTP APIs
Home-page: https://github.com/Waffles32/restclasses
Author: Forrest Button
Author-email: forrest.button@gmail.com
License: UNKNOWN
Platform: UNKNOWN
Classifier: Development Status :: 5 - Production/Stable
Classifier: Programming Language :: Python
Classifier: Programming Language :: Python :: 3
Classifier: Programming Language :: Python :: 3 :: Only
Classifier: License :: OSI Approved :: MIT License
Classifier: Operating System :: OS Independent
Requires-Python: >3.6
Requires-Dist: requests
